perturbation_classifiers/__init__.py
perturbation_classifiers/base.py
perturbation_classifiers/estimation.py
perturbation_classifiers/perc.py
perturbation_classifiers/perturbation.py
perturbation_classifiers/subconcept/__init__.py
perturbation_classifiers/subconcept/aggregation.py
perturbation_classifiers/subconcept/sperc.py
perturbation_classifiers/subconcept/clustering/__init__.py
perturbation_classifiers/subconcept/clustering/internal_validation.py
perturbation_classifiers/subconcept/clustering/small_cluster.py
perturbation_classifiers/util/__init__.py
perturbation_classifiers/util/dataset.py
perturbation_classifiers/util/prob_function.py
perturbation_classifiers-0.1.dist-info/LICENSE
perturbation_classifiers-0.1.dist-info/METADATA
perturbation_classifiers-0.1.dist-info/WHEEL
perturbation_classifiers-0.1.dist-info/top_level.txt
perturbation_classifiers-0.1.dist-info/RECORD
