Metadata-Version: 2.1
Name: perturbation-classifiers
Version: 0.1
Summary: Implementation of perturbation-based classifiers
Home-page: https://github.com/rjos/perturbation-classifiers
Author: Rodolfo J. O. Soares
Author-email: rodolfoj.soares@gmail.com
Maintainer: Rodolfo J. O. Soares
Maintainer-email: rodolfoj.soares@gmail.com
License: MIT
Platform: UNKNOWN
Classifier: Development Status :: 4 - Beta
Classifier: Intended Audience :: Developers
Classifier: Intended Audience :: Science/Research
Classifier: Programming Language :: Python :: 3.7
Classifier: Topic :: Scientific/Engineering :: Artificial Intelligence
Requires-Python: >=3.7
License-File: LICENSE
Requires-Dist: scikit-learn (>=0.24.2)
Requires-Dist: numpy (>=1.21.2)
Requires-Dist: scipy (>=1.7.1)
Requires-Dist: matplotlib (>=3.4.3)
Requires-Dist: pandas (>=1.3.2)
Requires-Dist: gap-stat (>=2.0.1)
Requires-Dist: gapstat-rs (>=2.0.1)
